nonebot_plugin_akinator-1.0.3.dist-info/METADATA
nonebot_plugin_akinator-1.0.3.dist-info/WHEEL
nonebot_plugin_akinator-1.0.3.dist-info/entry_points.txt
nonebot_plugin_akinator-1.0.3.dist-info/licenses/LICENSE
nonebot_plugin_akinator/__init__.py
nonebot_plugin_akinator/__main__.py
nonebot_plugin_akinator/cli/__init__.py
nonebot_plugin_akinator/cli/patch_import.py
nonebot_plugin_akinator/cli/res/bot.py
nonebot_plugin_akinator/cli/res/patch_pw_import.py
nonebot_plugin_akinator/config.py
nonebot_plugin_akinator/const.py
nonebot_plugin_akinator/message.py
nonebot_plugin_akinator/render.py
nonebot_plugin_akinator/res/bg.png
nonebot_plugin_akinator/res/icon.woff2
nonebot_plugin_akinator/res/templates/answer.html.jinja
nonebot_plugin_akinator/res/templates/base.html.jinja
nonebot_plugin_akinator/res/templates/base_aki_lre.html.jinja
nonebot_plugin_akinator/res/templates/question.html.jinja
nonebot_plugin_akinator-1.0.3.dist-info/RECORD
