Metadata-Version: 2.1
Name: nonebot-plugin-akinator
Version: 1.0.3
Summary: Internet Genius - Akinator
Author-Email: LgCookie <lgc2333@126.com>
License: MIT
Project-URL: homepage, https://github.com/lgc2333/nonebot-plugin-akinator
Requires-Python: <4.0,>=3.9
Requires-Dist: nonebot2>=2.4.1
Requires-Dist: nonebot-plugin-alconna>=0.57.2
Requires-Dist: nonebot-plugin-waiter>=0.8.1
Requires-Dist: cookit[loguru,nonebot-alconna]>=0.11.0
Requires-Dist: fleep>=1.0.1
Requires-Dist: cooaki>=0.3.0.post1
Provides-Extra: image
Requires-Dist: nonebot-plugin-htmlrender>=0.6.5; extra == "image"
Requires-Dist: cookit[jinja,pw]>=0.11.0; extra == "image"
Provides-Extra: patchright
Requires-Dist: nonebot-plugin-htmlrender>=0.6.5; extra == "patchright"
Requires-Dist: cooaki[patchright]>=0.3.0.post1; extra == "patchright"
